{
  "$schema": "https://ui.shadcn.com/schema/registry-item.json",
  "name": "consent-solution-minimal-demo",
  "type": "registry:example",
  "author": "Koroflow (https://koroflow.com/components",
  "dependencies": [
    "@koroflow/core-react"
  ],
  "registryDependencies": [
    "consent-solution"
  ],
  "files": [
    {
      "path": "examples/consent-solution-minimal-demo.tsx",
      "content": "import PrivacyPopup from \"@/registry/default/components/consent/consent-solution\";\nimport { ConsentManagerProvider } from \"@koroflow/core-react\";\n\nexport default function PrivacyPopupMinimalDemo() {\n  return (\n    <ConsentManagerProvider\n      initialGdprTypes={[\n        \"necessary\",\n        \"marketing\",\n        \"functionality\",\n        \"measurement\",\n      ]}\n    >\n      <PrivacyPopup />\n    </ConsentManagerProvider>\n  );\n}\n",
      "type": "registry:example",
      "target": ""
    }
  ]
}